ImagePi/__init__.py
ImagePi-0.0.0.dist-info/LICENSE
ImagePi-0.0.0.dist-info/METADATA
ImagePi-0.0.0.dist-info/WHEEL
ImagePi-0.0.0.dist-info/top_level.txt
ImagePi-0.0.0.dist-info/RECORD
